trainstation/__init__.py
trainstation/base_optimizer.py
trainstation/cross_validation.py
trainstation/ensemble_optimizer.py
trainstation/fit_methods.py
trainstation/model.py
trainstation/oi.py
trainstation/optimizer.py
trainstation/split_bregman.py
trainstation/tools.py
trainstation-1.2.dist-info/licenses/LICENSE
trainstation-1.2.dist-info/METADATA
trainstation-1.2.dist-info/WHEEL
trainstation-1.2.dist-info/top_level.txt
trainstation-1.2.dist-info/RECORD
