Metadata-Version: 2.4
Name: trainstation
Version: 1.2
Summary: Convenient training of linear models
Author: The trainstation developers group
Maintainer: The trainstation developers group
License: MIT License
Project-URL: Documentation, https://trainstation.materialsmodeling.org
Project-URL: Repository, https://gitlab.com/materials-modeling/trainstation/
Classifier: Development Status :: 5 - Production/Stable
Classifier: Operating System :: OS Independent
Classifier: Programming Language :: Python :: 3 :: Only
Classifier: Programming Language :: Python :: 3
Classifier: Programming Language :: Python :: 3.9
Classifier: Programming Language :: Python :: 3.10
Classifier: Programming Language :: Python :: 3.11
Classifier: Programming Language :: Python :: 3.12
Classifier: Programming Language :: Python :: 3.13
Classifier: Intended Audience :: Science/Research
Classifier: Topic :: Scientific/Engineering :: Physics
Requires-Python: >=3.9
License-File: LICENSE
Requires-Dist: scipy
Requires-Dist: numpy>=1.12
Requires-Dist: scikit-learn
Dynamic: license-file
